fuggit
