Metadata-Version: 1.1
Name: fuggit
Version: 0.0.2
Summary: For managing that one annoying remote file you can't put under version control
Home-page: UNKNOWN
Author: James Polley
Author-email: jp@jamezpolley.com
License: Apache-2
Platform: UNKNOWN
Classifier: Development Status :: 4 - Beta
Classifier: Environment :: Console
Classifier: License :: OSI Approved :: Apache Software License
Classifier: Operating System :: OS Independent
Classifier: Programming Language :: Python
